<?xml version="1.0" encoding="UTF-8" standalone="yes"?>
<vehicle-container xmlns:xsi="http://www.w3.org/2001/XMLSchema-instance">
	<vehicle-list>
		<vehicle>
			<owner-details>
				<owner-type>CPR</owner-type>
				<cpr>770505635</cpr>
				<arabic-name>الاسم بالعربي</arabic-name>
				<english-name>English Name</english-name>
				<pobox>1111</pobox>
				<flat>1</flat>
				<building>1586</building>
				<block>1014</block>
				<road>1431</road>
				<area-code>AlHamla</area-code>
			</owner-details>
			<vehicle-details>
				<payment-method>F</payment-method>
				<make-id>93</make-id>
				<model-id>8915</model-id>
				<type-id>64</type-id>
				<colour1-id>9</colour1-id>
				<colour2-id>5</colour2-id>
				<country-of-origin>426</country-of-origin>
				<year-of-model>2015</year-of-model>
				<chassis-no>QAQR1M010</chassis-no>
				<engine-no>VQ35748219Y</engine-no>
				<horsepower>3500</horsepower>
				<number-of-cylinders>6</number-of-cylinders>
				<number-of-seats>7</number-of-seats>
				<steering-position>T</steering-position>
				<fuel-type>1</fuel-type>
				<weight>2040</weight>
				<no-of-axles>2</no-of-axles>
				<max-speed>240</max-speed>
				<speed-measure>1</speed-measure>
				<short-plate>1</short-plate>
				<long-plate>1</long-plate>
				<plate-type>01</plate-type>
			</vehicle-details>
			<insurance-details>
				<insurance-company-name>16</insurance-company-name>
				<policy-number>ABCDE12345</policy-number>
				<insurance-date-start>01-08-2017</insurance-date-start>
				<insurance-date-end>31-08-2018</insurance-date-end>
			</insurance-details>
		</vehicle>
		<vehicle>
			<owner-details>
				<owner-type>CR</owner-type>
				<cpr>1269802</cpr>
				<arabic-name>الاسم بالعربي</arabic-name>
				<english-name>English Name</english-name>
				<pobox>1111</pobox>
				<flat>1</flat>
				<building>1586</building>
				<block>1014</block>
				<road>1431</road>
				<area-code>AlHamla</area-code>
			</owner-details>
			<vehicle-details>
				<payment-method>F</payment-method>
				<make-id>93</make-id>
				<model-id>8915</model-id>
				<type-id>64</type-id>
				<colour1-id>9</colour1-id>
				<colour2-id>5</colour2-id>
				<country-of-origin>426</country-of-origin>
				<year-of-model>2015</year-of-model>
				<chassis-no>QAQR1M011</chassis-no>
				<engine-no>VQ35748219Y</engine-no>
				<horsepower>3500</horsepower>
				<number-of-cylinders>6</number-of-cylinders>
				<number-of-seats>7</number-of-seats>
				<steering-position>T</steering-position>
				<fuel-type>1</fuel-type>
				<weight>2040</weight>
				<no-of-axles>2</no-of-axles>
				<max-speed>240</max-speed>
				<speed-measure>1</speed-measure>
				<short-plate>1</short-plate>
				<long-plate>1</long-plate>
				<plate-type>01</plate-type>
			</vehicle-details>
			<insurance-details>
				<insurance-company-name>16</insurance-company-name>
				<policy-number>ABCDE12345</policy-number>
				<insurance-date-start>01-08-2017</insurance-date-start>
				<insurance-date-end>31-08-2018</insurance-date-end>
			</insurance-details>
		</vehicle>
		<vehicle>
			<owner-details>
				<owner-type>CPR</owner-type>
				<cpr>770505635</cpr>
				<arabic-name>الاسم بالعربي</arabic-name>
				<english-name>English Name</english-name>
				<pobox>1111</pobox>
				<flat>1</flat>
				<building>1586</building>
				<block>1014</block>
				<road>1431</road>
				<area-code>AlHamla</area-code>
			</owner-details>
			<vehicle-details>
				<payment-method>F</payment-method>
				<make-id>93</make-id>
				<model-id>8915</model-id>
				<type-id>64</type-id>
				<colour1-id>9</colour1-id>
				<colour2-id>5</colour2-id>
				<country-of-origin>426</country-of-origin>
				<year-of-model>2015</year-of-model>
				<chassis-no>QAQR1M012</chassis-no>
				<engine-no>VQ35748219Y</engine-no>
				<horsepower>3500</horsepower>
				<number-of-cylinders>6</number-of-cylinders>
				<number-of-seats>7</number-of-seats>
				<steering-position>T</steering-position>
				<fuel-type>2</fuel-type>
				<weight>2040</weight>
				<no-of-axles>2</no-of-axles>
				<max-speed>240</max-speed>
				<speed-measure>2</speed-measure>
				<short-plate>1</short-plate>
				<long-plate>1</long-plate>
				<plate-type>01</plate-type>
			</vehicle-details>
			<insurance-details>
				<insurance-company-name>16</insurance-company-name>
				<policy-number>ABCDE12345</policy-number>
				<insurance-date-start>01-08-2017</insurance-date-start>
				<insurance-date-end>31-08-2018</insurance-date-end>
			</insurance-details>
		</vehicle>
		<vehicle>
			<owner-details>
				<owner-type>CR</owner-type>
				<cpr>1269802</cpr>
				<arabic-name>الاسم بالعربي</arabic-name>
				<english-name>English Name</english-name>
				<pobox>1111</pobox>
				<flat>1</flat>
				<building>1586</building>
				<block>1014</block>
				<road>1431</road>
				<area-code>AlHamla</area-code>
			</owner-details>
			<vehicle-details>
				<payment-method>F</payment-method>
				<make-id>93</make-id>
				<model-id>8915</model-id>
				<type-id>64</type-id>
				<colour1-id>9</colour1-id>
				<colour2-id>5</colour2-id>
				<country-of-origin>426</country-of-origin>
				<year-of-model>2015</year-of-model>
				<chassis-no>QAQR1M013</chassis-no>
				<engine-no>VQ35748219Y</engine-no>
				<horsepower>3500</horsepower>
				<number-of-cylinders>6</number-of-cylinders>
				<number-of-seats>7</number-of-seats>
				<steering-position>F</steering-position>
				<fuel-type>1</fuel-type>
				<weight>2040</weight>
				<no-of-axles>2</no-of-axles>
				<max-speed>240</max-speed>
				<speed-measure>1</speed-measure>
				<short-plate>1</short-plate>
				<long-plate>1</long-plate>
				<plate-type>01</plate-type>
			</vehicle-details>
			<insurance-details>
				<insurance-company-name>16</insurance-company-name>
				<policy-number>ABCDE12345</policy-number>
				<insurance-date-start>01-08-2017</insurance-date-start>
				<insurance-date-end>31-08-2018</insurance-date-end>
			</insurance-details>
		</vehicle>
		<vehicle>
			<owner-details>
				<owner-type>CPR</owner-type>
				<cpr>770505635</cpr>
				<arabic-name>الاسم بالعربي</arabic-name>
				<english-name>English Name</english-name>
				<pobox>1111</pobox>
				<flat>1</flat>
				<building>1586</building>
				<block>1014</block>
				<road>1431</road>
				<area-code>AlHamla</area-code>
			</owner-details>
			<vehicle-details>
				<payment-method>F</payment-method>
				<make-id>93</make-id>
				<model-id>8915</model-id>
				<type-id>64</type-id>
				<colour1-id>9</colour1-id>
				<colour2-id>5</colour2-id>
				<country-of-origin>426</country-of-origin>
				<year-of-model>2015</year-of-model>
				<chassis-no>QAQR1M014</chassis-no>
				<engine-no>VQ35748219Y</engine-no>
				<horsepower>3500</horsepower>
				<number-of-cylinders>6</number-of-cylinders>
				<number-of-seats>7</number-of-seats>
				<steering-position>T</steering-position>
				<fuel-type>1</fuel-type>
				<weight>2040</weight>
				<no-of-axles>2</no-of-axles>
				<max-speed>240</max-speed>
				<speed-measure>1</speed-measure>
				<short-plate>1</short-plate>
				<long-plate>1</long-plate>
				<plate-type>01</plate-type>
			</vehicle-details>
			<insurance-details>
				<insurance-company-name>16</insurance-company-name>
				<policy-number>ABCDE12345</policy-number>
				<insurance-date-start>01-08-2017</insurance-date-start>
				<insurance-date-end>31-08-2018</insurance-date-end>
			</insurance-details>
		</vehicle>
		<vehicle>
			<owner-details>
				<owner-type>CR</owner-type>
				<cpr>1269802</cpr>
				<arabic-name>الاسم بالعربي</arabic-name>
				<english-name>English Name</english-name>
				<pobox>1111</pobox>
				<flat>1</flat>
				<building>1586</building>
				<block>1014</block>
				<road>1431</road>
				<area-code>AlHamla</area-code>
			</owner-details>
			<vehicle-details>
				<payment-method>F</payment-method>
				<make-id>93</make-id>
				<model-id>8915</model-id>
				<type-id>64</type-id>
				<colour1-id>9</colour1-id>
				<colour2-id>5</colour2-id>
				<country-of-origin>426</country-of-origin>
				<year-of-model>2015</year-of-model>
				<chassis-no>QAQR1M015</chassis-no>
				<engine-no>VQ35748219Y</engine-no>
				<horsepower>3500</horsepower>
				<number-of-cylinders>6</number-of-cylinders>
				<number-of-seats>7</number-of-seats>
				<steering-position>T</steering-position>
				<fuel-type>2</fuel-type>
				<weight>2040</weight>
				<no-of-axles>2</no-of-axles>
				<max-speed>240</max-speed>
				<speed-measure>2</speed-measure>
				<short-plate>1</short-plate>
				<long-plate>1</long-plate>
				<plate-type>01</plate-type>
			</vehicle-details>
			<insurance-details>
				<insurance-company-name>16</insurance-company-name>
				<policy-number>ABCDE12345</policy-number>
				<insurance-date-start>01-08-2017</insurance-date-start>
				<insurance-date-end>31-08-2018</insurance-date-end>
			</insurance-details>
		</vehicle>
		<vehicle>
			<owner-details>
				<owner-type>CPR</owner-type>
				<cpr>770505635</cpr>
				<arabic-name>الاسم بالعربي</arabic-name>
				<english-name>English Name</english-name>
				<pobox>1111</pobox>
				<flat>1</flat>
				<building>1586</building>
				<block>1014</block>
				<road>1431</road>
				<area-code>AlHamla</area-code>
			</owner-details>
			<vehicle-details>
				<payment-method>F</payment-method>
				<make-id>93</make-id>
				<model-id>8915</model-id>
				<type-id>64</type-id>
				<colour1-id>9</colour1-id>
				<colour2-id>5</colour2-id>
				<country-of-origin>426</country-of-origin>
				<year-of-model>2015</year-of-model>
				<chassis-no>QAQR1M016</chassis-no>
				<engine-no>VQ35748219Y</engine-no>
				<horsepower>3500</horsepower>
				<number-of-cylinders>6</number-of-cylinders>
				<number-of-seats>7</number-of-seats>
				<steering-position>F</steering-position>
				<fuel-type>1</fuel-type>
				<weight>2040</weight>
				<no-of-axles>2</no-of-axles>
				<max-speed>240</max-speed>
				<speed-measure>1</speed-measure>
				<short-plate>1</short-plate>
				<long-plate>1</long-plate>
				<plate-type>01</plate-type>
			</vehicle-details>
			<insurance-details>
				<insurance-company-name>16</insurance-company-name>
				<policy-number>ABCDE12345</policy-number>
				<insurance-date-start>01-08-2017</insurance-date-start>
				<insurance-date-end>31-08-2018</insurance-date-end>
			</insurance-details>
		</vehicle>
		<vehicle>
			<owner-details>
				<owner-type>CR</owner-type>
				<cpr>1269802</cpr>
				<arabic-name>الاسم بالعربي</arabic-name>
				<english-name>English Name</english-name>
				<pobox>1111</pobox>
				<flat>1</flat>
				<building>1586</building>
				<block>1014</block>
				<road>1431</road>
				<area-code>AlHamla</area-code>
			</owner-details>
			<vehicle-details>
				<payment-method>F</payment-method>
				<make-id>93</make-id>
				<model-id>8915</model-id>
				<type-id>64</type-id>
				<colour1-id>9</colour1-id>
				<colour2-id>5</colour2-id>
				<country-of-origin>426</country-of-origin>
				<year-of-model>2015</year-of-model>
				<chassis-no>QAQR1M017</chassis-no>
				<engine-no>VQ35748219Y</engine-no>
				<horsepower>3500</horsepower>
				<number-of-cylinders>6</number-of-cylinders>
				<number-of-seats>7</number-of-seats>
				<steering-position>T</steering-position>
				<fuel-type>2</fuel-type>
				<weight>2040</weight>
				<no-of-axles>2</no-of-axles>
				<max-speed>240</max-speed>
				<speed-measure>1</speed-measure>
				<short-plate>1</short-plate>
				<long-plate>1</long-plate>
				<plate-type>01</plate-type>
			</vehicle-details>
			<insurance-details>
				<insurance-company-name>16</insurance-company-name>
				<policy-number>ABCDE12345</policy-number>
				<insurance-date-start>01-08-2017</insurance-date-start>
				<insurance-date-end>31-08-2018</insurance-date-end>
			</insurance-details>
		</vehicle>
		<vehicle>
			<owner-details>
				<owner-type>CPR</owner-type>
				<cpr>770505635</cpr>
				<arabic-name>الاسم بالعربي</arabic-name>
				<english-name>English Name</english-name>
				<pobox>1111</pobox>
				<flat>1</flat>
				<building>1586</building>
				<block>1014</block>
				<road>1431</road>
				<area-code>AlHamla</area-code>
			</owner-details>
			<vehicle-details>
				<payment-method>F</payment-method>
				<make-id>93</make-id>
				<model-id>8915</model-id>
				<type-id>64</type-id>
				<colour1-id>9</colour1-id>
				<colour2-id>5</colour2-id>
				<country-of-origin>426</country-of-origin>
				<year-of-model>2015</year-of-model>
				<chassis-no>QAQR1M018</chassis-no>
				<engine-no>VQ35748219Y</engine-no>
				<horsepower>3500</horsepower>
				<number-of-cylinders>6</number-of-cylinders>
				<number-of-seats>7</number-of-seats>
				<steering-position>T</steering-position>
				<fuel-type>1</fuel-type>
				<weight>2040</weight>
				<no-of-axles>2</no-of-axles>
				<max-speed>240</max-speed>
				<speed-measure>1</speed-measure>
				<short-plate>1</short-plate>
				<long-plate>1</long-plate>
				<plate-type>01</plate-type>
			</vehicle-details>
			<insurance-details>
				<insurance-company-name>16</insurance-company-name>
				<policy-number>ABCDE12345</policy-number>
				<insurance-date-start>01-08-2017</insurance-date-start>
				<insurance-date-end>31-08-2018</insurance-date-end>
			</insurance-details>
		</vehicle>
		<vehicle>
			<owner-details>
				<owner-type>CR</owner-type>
				<cpr>1269802</cpr>
				<arabic-name>الاسم بالعربي</arabic-name>
				<english-name>English Name</english-name>
				<pobox>1111</pobox>
				<flat>1</flat>
				<building>1586</building>
				<block>1014</block>
				<road>1431</road>
				<area-code>AlHamla</area-code>
			</owner-details>
			<vehicle-details>
				<payment-method>F</payment-method>
				<make-id>93</make-id>
				<model-id>8915</model-id>
				<type-id>64</type-id>
				<colour1-id>9</colour1-id>
				<colour2-id>5</colour2-id>
				<country-of-origin>426</country-of-origin>
				<year-of-model>2015</year-of-model>
				<chassis-no>QAQR1M019</chassis-no>
				<engine-no>VQ35748219Y</engine-no>
				<horsepower>3500</horsepower>
				<number-of-cylinders>6</number-of-cylinders>
				<number-of-seats>7</number-of-seats>
				<steering-position>T</steering-position>
				<fuel-type>1</fuel-type>
				<weight>2040</weight>
				<no-of-axles>2</no-of-axles>
				<max-speed>240</max-speed>
				<speed-measure>1</speed-measure>
				<short-plate>1</short-plate>
				<long-plate>1</long-plate>
				<plate-type>01</plate-type>
			</vehicle-details>
			<insurance-details>
				<insurance-company-name>16</insurance-company-name>
				<policy-number>ABCDE12345</policy-number>
				<insurance-date-start>01-08-2017</insurance-date-start>
				<insurance-date-end>31-08-2018</insurance-date-end>
			</insurance-details>
		</vehicle>
	</vehicle-list>
</vehicle-container>